unotify/__init__.py
unotify/core.py
unotify/urgencies.py
unotify-1.1.dist-info/LICENSE
unotify-1.1.dist-info/METADATA
unotify-1.1.dist-info/WHEEL
unotify-1.1.dist-info/top_level.txt
unotify-1.1.dist-info/RECORD
