Metadata-Version: 2.1
Name: unotify
Version: 1.1
Summary: Simple Python Linux/Ubuntu Notify Package
Home-page: UNKNOWN
Author: Gowixx
Author-email: <ItsGowixx@gmail.com>
License: UNKNOWN
Keywords: python,notify,toast,notification
Platform: UNKNOWN
Classifier: Programming Language :: Python :: 3
Classifier: License :: OSI Approved :: MIT License
Classifier: Operating System :: POSIX
License-File: LICENSE
